flask_oauth_tokeninfo
